jcjy_authing/__init__.py
jcjy_authing/_version.py
jcjy_authing/labextension/package.json
jcjy_authing/labextension/static/509.058c6c6ea09b515f9262.js
jcjy_authing/labextension/static/728.4575444173a1413d1977.js
jcjy_authing/labextension/static/remoteEntry.14ca9f9792ee6737ba98.js
jcjy_authing/labextension/static/style.js
jcjy_authing/labextension/static/third-party-licenses.json
jcjy_authing-0.1.0.data/data/share/jupyter/labextensions/jcjy-authing/package.json
jcjy_authing-0.1.0.data/data/share/jupyter/labextensions/jcjy-authing/static/509.058c6c6ea09b515f9262.js
jcjy_authing-0.1.0.data/data/share/jupyter/labextensions/jcjy-authing/static/728.4575444173a1413d1977.js
jcjy_authing-0.1.0.data/data/share/jupyter/labextensions/jcjy-authing/static/remoteEntry.14ca9f9792ee6737ba98.js
jcjy_authing-0.1.0.data/data/share/jupyter/labextensions/jcjy-authing/static/style.js
jcjy_authing-0.1.0.data/data/share/jupyter/labextensions/jcjy-authing/static/third-party-licenses.json
jcjy_authing-0.1.0.data/data/share/jupyter/labextensions/jcjy-authing/install.json
jcjy_authing-0.1.0.dist-info/METADATA
jcjy_authing-0.1.0.dist-info/WHEEL
jcjy_authing-0.1.0.dist-info/licenses/LICENSE
jcjy_authing-0.1.0.dist-info/RECORD
